AUTHORS
CHANGES.rst
CONTRIBUTING.rst
LICENSE
MANIFEST.in
README.rst
setup.py
docs/Makefile
docs/conf.py
docs/contribute.rst
docs/examples.rst
docs/index.rst
docs/install.rst
docs/releases.rst
epfl_sphinx_theme.egg-info/PKG-INFO
epfl_sphinx_theme.egg-info/SOURCES.txt
epfl_sphinx_theme.egg-info/dependency_links.txt
epfl_sphinx_theme.egg-info/not-zip-safe
epfl_sphinx_theme.egg-info/requires.txt
epfl_sphinx_theme.egg-info/top_level.txt
epfl_theme/__init__.py
epfl_theme/theme/epfl/layout.html
epfl_theme/theme/epfl/search.html
epfl_theme/theme/epfl/searchresults.html
epfl_theme/theme/epfl/sourcelink.html
epfl_theme/theme/epfl/theme.conf
epfl_theme/theme/epfl/static/epfl-navigation.js
epfl_theme/theme/epfl/static/jquery.hoverIntent.minified.js
epfl_theme/theme/epfl/static/jquery.treeview.minified.js
epfl_theme/theme/epfl/static/pygments-epfl.css
epfl_theme/theme/epfl/static/searchtools.js_t
epfl_theme/theme/epfl/static/sphinx-epfl.css_t