Metadata-Version: 1.0
Name: epfl-sphinx-theme
Version: 1.1.1
Summary: A Sphinx theme for EPFL (web2010)
Home-page: http://kis-doc.epfl.ch/sphinx/
Author: EPFL/SI/DIT/KIS
Author-email: webmaster@epfl.ch
License: GNU General Public License (GPL)
Keywords: sphinx extension theme epfl
Platform: UNKNOWN
Classifier: Development Status :: 5 - Production/Stable
Classifier: Intended Audience :: Developers
Classifier: License :: OSI Approved :: GNU General Public License (GPL)
Classifier: Operating System :: OS Independent
Classifier: Programming Language :: Python :: 2.5
Classifier: Programming Language :: Python :: 2.6
Classifier: Programming Language :: Python :: 2.7
Classifier: Programming Language :: Python :: 3
Classifier: Topic :: Documentation
Classifier: Topic :: Software Development :: Documentation
